metagen/__init__.py
metagen/framework/__init__.py
metagen/framework/facades.py
metagen/framework/connector/__init__.py
metagen/framework/connector/connector.py
metagen/framework/domain/__init__.py
metagen/framework/domain/bounds.py
metagen/framework/domain/core.py
metagen/framework/domain/literals.py
metagen/framework/domain/preconditions.py
metagen/framework/solution/__init__.py
metagen/framework/solution/base_solution.py
metagen/framework/solution/bounds.py
metagen/framework/solution/devsolution.py
metagen/framework/solution/literals.py
metagen/framework/solution/types/__init__.py
metagen/framework/solution/types/base.py
metagen/framework/solution/types/categorical.py
metagen/framework/solution/types/integer.py
metagen/framework/solution/types/real.py
metagen/framework/solution/types/structure.py
metagen/metaheuristics/__init__.py
metagen/metaheuristics/pso.py
metagen/metaheuristics/cvoa/__init__.py
metagen/metaheuristics/cvoa/cvoa.py
metagen/metaheuristics/ga/__init__.py
metagen/metaheuristics/ga/ga.py
metagen/metaheuristics/ga/ga_types.py
metagen/metaheuristics/random/__init__.py
metagen/metaheuristics/random/random_search.py
MetaGen_datalabupo-0.0.3.dist-info/LICENSE
MetaGen_datalabupo-0.0.3.dist-info/METADATA
MetaGen_datalabupo-0.0.3.dist-info/WHEEL
MetaGen_datalabupo-0.0.3.dist-info/top_level.txt
MetaGen_datalabupo-0.0.3.dist-info/RECORD
