Metadata-Version: 2.1
Name: MetaGen-datalabupo
Version: 0.0.3
Summary: A Python Package for Hyperparameter Tuning in Machine and Deep Learning Models Based on the Coronavirus Optimization Algorithm
Home-page: https://github.com/DataLabUPO/MetaGen
Author: Data Science & Big Data Rerearch Lab
Author-email: datalab@upo.es
Project-URL: Bug Tracker, https://github.com/DataLabUPO/MetaGen/issues
Classifier: Programming Language :: Python :: 3
Classifier: License :: OSI Approved :: MIT License
Classifier: Operating System :: OS Independent
Requires-Python: >=3.10
License-File: LICENSE
